pout/__init__.py
pout/__main__.py
pout/compat.py
pout/environ.py
pout/interface.py
pout/path.py
pout/reflect.py
pout/utils.py
pout/value.py
pout-3.2.0.dist-info/licenses/LICENSE.txt
pout-3.2.0.dist-info/METADATA
pout-3.2.0.dist-info/WHEEL
pout-3.2.0.dist-info/entry_points.txt
pout-3.2.0.dist-info/top_level.txt
pout-3.2.0.dist-info/RECORD
