Metadata-Version: 2.4
Name: pout
Version: 3.2.0
Summary: Prints out python variables in an easy to read way, handy for debugging
Author-email: Jay Marcyes <jay@marcyes.com>
License-Expression: MIT
Project-URL: Homepage, https://github.com/Jaymon/pout
Project-URL: Repository, https://github.com/Jaymon/pout
Classifier: Development Status :: 5 - Production/Stable
Classifier: Environment :: Plugins
Classifier: Intended Audience :: Developers
Classifier: Operating System :: OS Independent
Classifier: Topic :: Software Development :: Testing
Classifier: Programming Language :: Python :: 3
Requires-Python: >=3.10
License-File: LICENSE.txt
Provides-Extra: tests
Requires-Dist: testdata; extra == "tests"
Dynamic: license-file
